pergolaprojecttools/__init__.py
pergolaprojecttools/config_util.py
pergolaprojecttools/error_util.py
pergolaprojecttools/exceptions.py
pergolaprojecttools/trace_util.py
pergolaprojecttools/log/__init__.py
pergolaprojecttools/log/log.py
pergola_projecttools-2.2.0.dist-info/LICENSE
pergola_projecttools-2.2.0.dist-info/METADATA
pergola_projecttools-2.2.0.dist-info/WHEEL
pergola_projecttools-2.2.0.dist-info/top_level.txt
pergola_projecttools-2.2.0.dist-info/RECORD
