Metadata-Version: 2.1
Name: pergola-projecttools
Version: 2.2.0
Summary: Helpful tools and utils for applications running inside of Pergola Cloud
Author-email: Datasophie GmbH <contact@datasophie.de>, Dennis Hauser <dennis.hauser@brandcompete.com>
Project-URL: Pergola-Login, https://console.pergola.cloud
Project-URL: Documentation, https://docs.pergola.cloud
Project-URL: Homepage, https://pergola.cloud
Project-URL: Source, https://github.com/datasophie/pergola-projecttools-python
Keywords: pergola,util,tool,utils,tools
Classifier: Programming Language :: Python :: 3
Classifier: License :: OSI Approved :: Apache Software License
Requires-Python: >=3.9
License-File: LICENSE
Requires-Dist: psutil
